.gitignore
AUTHORS
LICENSE
MANIFEST.in
README.rst
ez_setup.py
fabfile.py
setup.py
doc/source/changelog.rst
doc/source/conf.py
doc/source/configuration.rst
doc/source/custom_codecs.rst
doc/source/custom_storages.rst
doc/source/getting_involved.rst
doc/source/index.rst
doc/source/installation.rst
doc/source/usage.rst
doc/source/_static/.gitkeep
doc/source/_templates/layout.html
doc/source/modules/context_processors.rst
doc/source/modules/decorators.rst
doc/source/modules/index.rst
doc/source/modules/middleware.rst
doc/source/modules/models.rst
doc/source/modules/codec/index.rst
doc/source/modules/codec/json_impl.rst
doc/source/modules/codec/json_zlib_impl.rst
doc/source/modules/codec/pickle_impl.rst
doc/source/modules/storage/cookie.rst
doc/source/modules/storage/index.rst
doc/source/modules/storage/session.rst
src/django_flash.egg-info/PKG-INFO
src/django_flash.egg-info/SOURCES.txt
src/django_flash.egg-info/dependency_links.txt
src/django_flash.egg-info/not-zip-safe
src/django_flash.egg-info/requires.txt
src/django_flash.egg-info/top_level.txt
src/djangoflash/__init__.py
src/djangoflash/context_processors.py
src/djangoflash/decorators.py
src/djangoflash/middleware.py
src/djangoflash/models.py
src/djangoflash/views.py
src/djangoflash/codec/__init__.py
src/djangoflash/codec/json_impl.py
src/djangoflash/codec/json_zlib_impl.py
src/djangoflash/codec/pickle_impl.py
src/djangoflash/storage/__init__.py
src/djangoflash/storage/cookie.py
src/djangoflash/storage/session.py
src/djangoflash/tests/__init__.py
src/djangoflash/tests/codec.py
src/djangoflash/tests/context_processors.py
src/djangoflash/tests/decorators.py
src/djangoflash/tests/models.py
src/djangoflash/tests/storage.py
src/djangoflash/tests/suite.py
src/djangoflash/tests/testproj/__init__.py
src/djangoflash/tests/testproj/manage.py
src/djangoflash/tests/testproj/settings.py
src/djangoflash/tests/testproj/urls.py
src/djangoflash/tests/testproj/app/__init__.py
src/djangoflash/tests/testproj/app/models.py
src/djangoflash/tests/testproj/app/tests.py
src/djangoflash/tests/testproj/app/urls.py
src/djangoflash/tests/testproj/app/views.py
src/djangoflash/tests/testproj/media/test.css
src/djangoflash/tests/testproj/templates/simple.html