Metadata-Version: 1.0
Name: django-flash
Version: 1.8
Summary: Django-flash is a simple Django extension which provides support for Rails-like flash messages.
Home-page: http://djangoflash.destaquenet.com/
Author: Daniel Fernandes Martins
Author-email: daniel@destaquenet.com
License: BSD
Keywords: django,flash,session,scope,context,contrib
Platform: Any
Classifier: Development Status :: 5 - Production/Stable
Classifier: Intended Audience :: Developers
Classifier: License :: OSI Approved :: BSD License
Classifier: Natural Language :: English
Classifier: Operating System :: OS Independent
Classifier: Programming Language :: Python
Classifier: Framework :: Django
Classifier: Topic :: Internet :: WWW/HTTP
